sbt/__init__.py
sbt/__main__.py
sbt/commands/__init__.py
sbt/commands/build.py
sbt/commands/check_release.py
sbt/commands/git.py
sbt/commands/install.py
sbt/commands/list.py
sbt/config.py
sbt/misc.py
sbt/package/__init__.py
sbt/package/discovery.py
sbt/package/graph.py
sbt/package/package.py
sbt/registry/__init__.py
sbt/registry/pypi.py
sbt/registry/registry.py
sbt/vcs/__init__.py
sbt/vcs/git.py
pbt_simple-2.1.2.dist-info/LICENSE
pbt_simple-2.1.2.dist-info/METADATA
pbt_simple-2.1.2.dist-info/WHEEL
pbt_simple-2.1.2.dist-info/entry_points.txt
pbt_simple-2.1.2.dist-info/RECORD
