Metadata-Version: 2.1
Name: pbt-simple
Version: 2.1.2
Summary: A simpler version of [PBT](https://github.com/binh-vu/pbt) for installing a package (and its local dependencies in editable mode) and build extension modules written in PYO3.
Home-page: https://github.com/binh-vu/pbt-simple
License: MIT
Author: Binh Vu
Author-email: binh@toan2.com
Requires-Python: >=3.9,<4.0
Classifier: License :: OSI Approved :: MIT License
Classifier: Programming Language :: Python :: 3
Classifier: Programming Language :: Python :: 3.9
Classifier: Programming Language :: Python :: 3.10
Classifier: Programming Language :: Python :: 3.11
Classifier: Programming Language :: Python :: 3.12
Classifier: Programming Language :: Python :: 3.13
Requires-Dist: click (>=8.1.7,<9.0.0)
Requires-Dist: loguru (>=0.7.2,<0.8.0)
Requires-Dist: networkx (>=3.2.1,<4.0.0)
Requires-Dist: orjson (>=3.9.9,<4.0.0)
Requires-Dist: poetry (>=1.7.1,<2.0.0)
Requires-Dist: requests (>=2.31.0,<3.0.0)
Requires-Dist: rich (>=13.9.4,<14.0.0)
Requires-Dist: semver (>=3.0.2,<4.0.0)
Requires-Dist: tomlkit (>=0.12.1,<0.13.0)
Requires-Dist: tqdm (>=4.66.1,<5.0.0)
Requires-Dist: typing-extensions (>=4.8.0,<5.0.0)
Project-URL: Repository, https://github.com/binh-vu/pbt-simple
